[
  {
    "id": "kc-1",
    "name": "Identify that PascalCase is used for react component names",
    "pKnown": 0.2,
    "pWillLearn": 0.15,
    "knowledgeLevel": "none"
  },
  {
    "id": "kc-2",
    "name": "Identify that a react component must return valid JSX or null",
    "pKnown": 0.3,
    "pWillLearn": 0.2,
    "knowledgeLevel": "none"
  },
  {
    "id": "kc-3",
    "name": "Identify the JSX syntax needed to call a component",
    "pKnown": 0.1,
    "pWillLearn": 0.3,
    "knowledgeLevel": "none"
  },
  {
    "id": "kc-4",
    "name": "Identify why the useState hook is necessary",
    "pKnown": 0.1,
    "pWillLearn": 0.25,
    "knowledgeLevel": "none"
  },
  {
    "id": "kc-5",
    "name": "Determine when you need to use the useState hook",
    "pKnown": 0.05,
    "pWillLearn": 0.3,
    "knowledgeLevel": "none"
  },
  {
    "id": "kc-6",
    "name": "Identify that useState returns a state variable",
    "pKnown": 0.1,
    "pWillLearn": 0.4,
    "knowledgeLevel": "none"
  },
  {
    "id": "kc-7",
    "name": "Identify that useState returns a state function",
    "pKnown": 0.2,
    "pWillLearn": 0.3,
    "knowledgeLevel": "none"
  },
  {
    "id": "kc-8",
    "name": "Identify that useState has to be called at the top of your component",
    "pKnown": 0.1,
    "pWillLearn": 0.2,
    "knowledgeLevel": "none"
  },
  {
    "id": "kc-9",
    "name": "Provide a default value to useState",
    "pKnown": 0.2,
    "pWillLearn": 0.2,
    "knowledgeLevel": "none"
  },
  {
    "id": "kc-10",
    "name": "Provide type information to useState",
    "pKnown": 0.15,
    "pWillLearn": 0.25,
    "knowledgeLevel": "none"
  },
  {
    "id": "kc-11",
    "name": "Use array destructing to store the returned values",
    "pKnown": 0.2,
    "pWillLearn": 0.2,
    "knowledgeLevel": "none"
  },
  {
    "id": "kc-12",
    "name": "Identify which value is the state variable",
    "pKnown": 0.2,
    "pWillLearn": 0.2,
    "knowledgeLevel": "none"
  },
  {
    "id": "kc-13",
    "name": "Identify which value is the state function",
    "pKnown": 0.2,
    "pWillLearn": 0.2,
    "knowledgeLevel": "none"
  }
]
